dirtreedigest/__config__.py
dirtreedigest/__init__.py
dirtreedigest/comparator.py
dirtreedigest/digester.py
dirtreedigest/main_compare.py
dirtreedigest/main_digest.py
dirtreedigest/reader.py
dirtreedigest/utils.py
dirtreedigest/walker.py
dirtreedigest/worker.py
DirTreeDigest-1.0.7.dist-info/METADATA
DirTreeDigest-1.0.7.dist-info/WHEEL
DirTreeDigest-1.0.7.dist-info/entry_points.txt
DirTreeDigest-1.0.7.dist-info/top_level.txt
DirTreeDigest-1.0.7.dist-info/RECORD
